boto3_assume/__init__.py
boto3_assume/aio_assume_refresh.py
boto3_assume/aio_core.py
boto3_assume/assume_refresh.py
boto3_assume/core.py
boto3_assume-0.1.2.dist-info/LICENSE
boto3_assume-0.1.2.dist-info/METADATA
boto3_assume-0.1.2.dist-info/WHEEL
boto3_assume-0.1.2.dist-info/top_level.txt
boto3_assume-0.1.2.dist-info/RECORD
