Metadata-Version: 2.1
Name: boto3-assume
Version: 0.1.2
Summary: Easily create boto3/aioboto3 assume role sessions with automatic credential refreshing.
Home-page: https://github.com/btemplep/boto3-assume
Author: Brandon Temple Paul
Author-email: btemplepgit@gmail.com
License: Apache License 2.0
Project-URL: Repository, https://github.com/btemplep/boto3-assume
Keywords: aio,aioboto3,aiobotocore,assume,async,asyncio,aws,boto3,botocore,credentials,creds,iam,refresh,refreshable,role,sdk
Classifier: Development Status :: 5 - Production/Stable
Classifier: License :: OSI Approved :: Apache Software License
Classifier: Natural Language :: English
Classifier: Operating System :: OS Independent
Classifier: Programming Language :: Python :: 3
Classifier: Programming Language :: Python :: 3 :: Only
Classifier: Programming Language :: Python :: 3.8
Classifier: Programming Language :: Python :: 3.9
Classifier: Programming Language :: Python :: 3.10
Classifier: Programming Language :: Python :: 3.11
Classifier: Programming Language :: Python :: 3.12
Classifier: Programming Language :: Python :: Implementation :: CPython
Classifier: Topic :: Software Development :: Libraries :: Python Modules
License-File: LICENSE
Provides-Extra: dev
Requires-Dist: aioboto3 ; extra == 'dev'
Requires-Dist: build ; extra == 'dev'
Requires-Dist: coverage ; extra == 'dev'
Requires-Dist: moto[server] ; extra == 'dev'
Requires-Dist: nox ; extra == 'dev'
Requires-Dist: pytest ; extra == 'dev'
Requires-Dist: pytest-asyncio ; extra == 'dev'
Requires-Dist: pytest-cov ; extra == 'dev'
Requires-Dist: pytz ; extra == 'dev'
Requires-Dist: twine ; extra == 'dev'
